README.md
setup.py
ourkids_common_frontend.egg-info/PKG-INFO
ourkids_common_frontend.egg-info/SOURCES.txt
ourkids_common_frontend.egg-info/dependency_links.txt
ourkids_common_frontend.egg-info/requires.txt
ourkids_common_frontend.egg-info/top_level.txt
ourkids_f/ExceptionInterceptor.py
ourkids_f/NotAuthException.py
ourkids_f/NotFoundException.py
ourkids_f/Settings.py
ourkids_f/__init__.py
ourkids_f/interceptors.py
ourkids_f/load.py