Metadata-Version: 2.1
Name: ourkids-common-frontend
Version: 0.0.5
Summary: Librería para tener configuraciones y archivos comunes para la implementación y uso de servidores en flask.
Home-page: https://github.com/Jefry-bot/ourkids_f
Author: Jefry Zárate Ruíz
Author-email: jefryzarateruiz@gmail.com
License: MIT
Download-URL: https://github.com/Jefry-bot/ourkids_f/tarball/0.0.1
Keywords: testing,logging,example
Platform: UNKNOWN
